{
  "300001" :"创建云主机失败",
  "300002" :"从云盘创建云主机失败",
  "300003" :"从快照创建云主机失败",
  "300004" :"从快照组创建云主机失败",
  "300005" :"删除云主机失败",
  "300006" :"恢复已删除云主机失败",
  "300007" :"彻底删除云主机失败",
  "300008" :"查询云主机失败",
  "300009" :"启动云主机失败",
  "300010" :"停止云主机失败",
  "300011" :"重启云主机失败",
  "300012" :"暂停云主机失败",
  "300013" :"恢复暂停的云主机失败",
  "300014" :"重置云主机失败",
  "300015" :"热迁移云主机失败",
  "300016" :"查询共享磁盘所挂载的云主机失败",
  "300017" :"获取可热迁移的物理机列表失败",
  "300018" :"获取可选择的主存储失败",
  "300019" :"获取云主机可加载ISO列表失败",
  "300020" :"获取ISO可加载云主机列表失败",
  "300021" :"加载ISO到云主机失败",
  "300022" :"卸载云主机上的ISO失败",
  "300023" :"获取云主机可加载云盘列表失败",
  "300024" :"获取云主机可加载L3网络列表失败",
  "300025" :"加载L3网络到云主机失败",
  "300026" :"从云主机卸载网络失败",
  "300027" : "创建云主机网卡失败",
  "300028" : "加载网卡到云主机失败",
  "300029" : "删除云主机网卡失败",
  "300030" :"查询云主机网卡失败",
  "300031" : "获取网卡加载的网络服务名称失败",
  "300032" : "修改云主机网卡三层网络失败",
  "300033" : "获取云主机网卡可挂载的三层网络",
  "300034" :"设置云主机网卡限速失败",
  "300035" :"获取云主机网卡限速失败",
  "300036" :"取消云主机网卡限速失败",
  "300037" :"获取相互依赖的镜像和L3网络失败",
  "300038" :"设置云主机ssh_key失败",
  "300039" :"获取云主机ssh_key失败",
  "300040" :"删除云主机ssh_key失败",
  "300041" :"变更云主机密码失败",
  "300042" :"设置云主机控制台密码失败",
  "300043" :"获取云主机控制台密码失败",
  "300044" :"删除云主机控制台密码失败",
  "300045" :"获取云主机控制台地址和访问协议失败",
  "300046" :"设置云主机Hostname失败",
  "300047" :"获取云主机Hostname失败",
  "300048" :"删除云主机Hostname失败",
  "300049" :"创建启动云主机的定时任务失败",
  "300050" :"创建停止云主机的定时任务失败",
  "300051" :"创建重启云主机的定时任务失败",
  "300052" :"获取云主机启动设备列表失败",
  "300053" :"指定云主机启动设备失败",
  "300054" :"获取目的地列表失败",
  "300055" :"获取云主机可启动目的地列表失败",
  "300056" :"指定云主机IP失败",
  "300057" :"删除云主机指定IP失败",
  "300058" :"获取云主机能力失败",
  "300059" :"更新云主机信息失败",
  "300060" :"克隆云主机到指定物理机失败",
  "300061" : "设置云主机时钟同步失败",
  "300062" :"设置云主机高可用级别失败",
  "300063" :"获取云主机高可用级别失败",
  "300064" :"取消云主机高可用失败",
  "300065" :"获取云主机Qga失败",
  "300066" :"设置云主机Qga失败",
  "300067" :"获取云主机RDP开关状态失败",
  "300068" :"设置云主机RDP开关状态失败",
  "300069" :"获取云主机支持的屏幕数失败",
  "300070" :"设置云主机支持的屏幕数失败",
  "300071" :"修改云主机根云盘失败",
  "300072" :"获取候选镜像列表失败",
  "300073" :"更新云主机mac地址失败",
  "300074" :"设置云主机防IP欺骗启用状态失败",
  "300075" :"为云主机创建CDROM失败",
  "300076" :"删除CDROM失败",
  "300077" : "修改CDROM失败",
  "300078" :"设置云主机默认CDROM失败",
  "300079" :"查询CDROM清单失败",
  "300080" :"更改云主机优先级级别失败",
  "300081" :"设置云主机显存失败",
  "300082" :"设置云主机虚拟声卡类型失败",
  "300083" :"获取spice的CA证书失败",
  "300084" :"为云主机加载增强工具镜像失败",
  "300085" :"获取云主机可用的最新增强工具失败",
  "300086" :"获取云主机内部增强工具的信息失败",
  "300087" :"获取云主机第一启动项失败",
  "300088" :"设置网卡型号失败",
  "300089" :"获取云主机设备地址失败",
  "300090" :"批量获取云主机能力失败",
  "300091" :"设置云主机vNUMA失败",
  "300092" :"获取VM Numa开关状态失败",
  "300093" :"查询云主机的vNUMA拓扑信息失败",
  "300094" :"设置云主机Emulator Pinning功能失败",
  "300095" :"获取VM Emulator Pin在那些物理机的cpu上失败",
  "300096" :"创建云盘失败",
  "300097" :"删除云盘失败",
  "300098" :"彻底删除云盘失败",
  "300099" :"恢复云盘失败",
  "300100" :"开启或关闭云盘失败",
  "300101" :"从镜像创建云盘失败",
  "300102" :"从快照创建云盘失败",
  "300103" :"获取云盘清单失败",
  "300104" :"获取云盘格式失败",
  "300105" :"获取云盘支持的类型的能力失败",
  "300106" :"同步云盘大小失败",
  "300107" :"扩展根云盘失败",
  "300108" :"扩展数据云盘失败",
  "300109" :"修改云盘属性失败",
  "300110" :"设置云盘限速失败",
  "300111" :"获取云盘限速失败",
  "300112" :"取消云盘网卡限速失败",
  "300113" :"获取云盘可被加载的云主机列表失败",
  "300114" :"挂载云盘到云主机上失败",
  "300115" :"从云主机上卸载云盘失败",
  "300116" :"从云盘创建快照失败",
  "300117" :"查询云盘快照失败",
  "300118" :"查询快照树失败",
  "300119" :"更新云盘快照信息失败",
  "300120" :"删除云盘快照失败",
  "300121" :"将云盘回滚至指定快照失败",
  "300122" :"获取快照容量失败",
  "300123" :"快照瘦身失败",
  "300124" :"添加镜像失败",
  "300125" :"删除镜像失败",
  "300126" :"彻底删除镜像失败",
  "300127" :"查询镜像失败",
  "300128" :"恢复镜像失败",
  "300129" :"修改镜像状态失败",
  "300130" :"更新镜像信息失败",
  "300131" :"刷新镜像大小信息失败",
  "300132" :"获取镜像服务器候选失败",
  "300133" :"从根云盘创建根云盘镜像失败",
  "300134" :"从云盘快照创建根云盘镜像失败",
  "300135" :"从云盘创建数据云盘镜像失败",
  "300136" :"从云盘快照创建数据云盘镜像失败",
  "300137" :"获取镜像Qga失败",
  "300138" :"设置镜像Qga失败",
  "300139" :"设置镜像启动模式失败",
  "300140" :"获取上传镜像任务详情",
  "300141" :"创建亲和组失败",
  "300142" :"删除亲和组失败",
  "300143" :"查询亲和组失败",
  "300144" :"更新亲和组失败",
  "300145" :"添加云主机到亲和组失败",
  "300146" :"从亲和组移除云主机失败",
  "300147" :"改变亲和组的使用状态失败",
  "300148" :"获取可绑定云主机的亲和组失败",
  "300149" :"获取可绑定亲和组的云主机失败",
  "300150" :"创建云主机时获取可加入非亲和组失败",
  "300151" :"创建云主机规格失败",
  "300152" :"删除云主机规格失败",
  "300153" :"查询云主机规格失败",
  "300154" :"更改云主机规格失败",
  "300155" :"更新云主机规格失败",
  "300156" :"更改云主机规格的启用状态失败",
  "300157" :"创建云盘规格失败",
  "300158" :"删除云盘规格失败",
  "300159" :"查询云盘规格失败",
  "300160" :"更改云盘规格的启用状态失败",
  "300161" :"更新云盘规格失败",
  "300162" :"创建弹性伸缩组失败",
  "300163" :"删除弹性伸缩组失败",
  "300164" :"修改弹性伸缩组失败",
  "300165" :"查询弹性伸缩组失败",
  "300166" :"查询弹性伸缩组活动列表失败",
  "300167" :"创建伸缩组云主机扩容规则失败",
  "300168" :"创建伸缩组云主机缩容规则失败",
  "300169" :"删除伸缩规则失败",
  "300170" :"修改弹性伸缩组规则失败",
  "300171" :"修改伸缩组扩容规则失败",
  "300172" :"修改伸缩组缩容规则失败",
  "300173" :"查询伸缩规则失败",
  "300174" :"创建伸缩规则触发器失败",
  "300175" : "创建伸缩规则定时任务触发器失败",
  "300176" :"删除伸缩规则触发器失败",
  "300177" :"查询伸缩规则触发器列表失败",
  "300178" :"创建伸缩组云主机模块失败",
  "300179" :"将云主机模块添加到弹性伸缩组失败",
  "300180" :"删除伸缩组模板失败",
  "300181" :"卸载伸缩组模板失败",
  "300182" :"查询伸缩组云主机模板失败",
  "300183" :"手动删除弹性伸缩组内云主机失败",
  "300184" :"查询弹性伸缩组内云主机列表失败",
  "300185" :"修改弹性伸缩组启用状态失败",
  "300186" :"手动执行伸缩组规则失败",
  "300187" :"更新伸缩组实例信息失败",
  "300188" :"更新伸缩组云主机模板失败",
  "300189" :"创建快照组失败",
  "300190" :"创建快照组失败",
  "300191" :"更新快照组信息失败",
  "300192" :"查询快照组失败",
  "300193" :"检查快照组可用性失败",
  "300194" :"恢复快照组失败",
  "300195" :"解绑快照组失败",
  "300196" :"创建区域失败",
  "300197" :"删除区域失败",
  "300198" :"查询区域失败",
  "300199" :"更新区域失败",
  "300200" :"改变区域的可用状态失败",
  "300201" :"创建一个集群失败",
  "300202" :"删除一个集群失败",
  "300203" :"查询集群失败",
  "300204" :"更新集群失败",
  "300205" :"改变一个集群的可用状态失败",
  "300206" :"升级集群内物理机的操作系统失败失败",
  "300207" :"查询物理机失败",
  "300208" :"删除物理机失败",
  "300209" :"更新物理机信息失败",
  "300210" :"更新物理机启用状态失败",
  "300211" :"重连物理机失败",
  "300212" :"获取物理机分配策略失败",
  "300213" :"获取云主机虚拟化技术类型失败",
  "300214" :"更新KVM主机信息失败",
  "300215" :"添加KVM主机失败",
  "300216" :"KVM运行Shell命令失败",
  "300217" :"通过文件导入方式添加物理机失败",
  "300218" :"添加物理机文件语法检查失败",
  "300219" :"获取物理机物理网络信息失败",
  "300220" :"查询物理机Bond信息失败",
  "300221" :"查询物理机网卡信息失败",
  "300222" : "查询物理机的NUMA拓扑信息失败",
  "300223": "根据云主机需求获取物理机资源的分配信息失败",
  "300224" :"查询PCI设备失败",
  "300225" :"更新PCI设备失败",
  "300226" :"删除PCI设备失败",
  "300227" :"获取PCI设备列表失败",
  "300228" :"获取可加载PCI设备失败",
  "300229" :"绑定PCI设备到云主机失败",
  "300230" :"卸载PCI设备失败",
  "300231" :"创建PCI设备规格失败",
  "300232" :"删除PCI设备规格失败",
  "300233" :"查询PCI设备规格信息失败",
  "300234" :"查询PCI设备规格匹配失败",
  "300235" :"获取物理机lommu启用状态失败",
  "300236" :"更新物理机Iommu启用状态失败",
  "300237" :"获取物理机lommu就绪状态失败",
  "300238" :"将PCI设备规格加载到云主机失败",
  "300239" :"将PCI设备规格从云主机卸载失败",
  "300240" :"更新PCI设备规格失败",
  "300241" :"获取PCI设备规格候选列表失败",
  "300242" :"查询PCI设备规格失败",
  "300243" :"查询云主机与PCI设备规格的关联关系失败",
  "300244" :"虚拟化切分支持SR-IOV的PCI设备失败",
  "300245" :"虚拟化还原支持SR-IOV的PCI设备失败",
  "300246" :"虚拟化切分支持VFIO_MDEV的PCI设备失败",
  "300247" :"虚拟化还原支持VFIO_MDEV的PCI设备失败",
  "300248" :"查询PCI设备切分出的MDEV设备失败",
  "300249" :"将PCI设备切分出的MDEV设备绑定到云主机失败",
  "300250" :"将PCI设备切分出的MDEV设备从云主机卸载失败",
  "300251" :"更新PCI设备切分出的MDEV设备失败",
  "300252" :"获取可用的MDEV设备失败",
  "300253" :"查询PCI设备切分出的MDEV设备失败",
  "300254" :"将MDEV设备规格加载到云主机失败",
  "300255" :"将MDEV设备规格从云主机卸载失败",
  "300256" :"更新MDEV设备规格失败",
  "300257" :"获取可用的MDEV设备规格失败",
  "300258" :"查询云主机与MDEV设备规格的关联关系失败",
  "300259" :"获取云主机usb重定向开关失败",
  "300260" :"设置云主机usb重定向开关失败",
  "300261" :"云主机加载物理机USB设备失败",
  "300262" :"将云主机挂载的USB设备卸载失败",
  "300263" :"获取USB透传候选列表失败",
  "300264" :"查询USB设备失败",
  "300265" :"更新USB设备失败",
  "300266" :"L3网络中是否存在可用VF网卡失败",
  "300267" :"修改云主机网卡类型失败",
  "300268" :"删除主存储失败",
  "300269" :"查询物理机失败",
  "300270" :"向集群添加主存储失败",
  "300271" :"从集群卸载主存储失败",
  "300272" :"重连主存储失败",
  "300273" :"获取主存储容量失败",
  "300274" :"刷新主存储容量失败",
  "300275" :"更改主存储状态失败",
  "300276" :"更新主存储信息失败",
  "300277" :"清除主存储镜像缓存失败",
  "300278" :"获取主存储分配策略清单失败",
  "300279" :"获取主存储类型列表失败",
  "300280" :"获取候选列表失败",
  "300281" : "获取跨存储迁移可选物理机列表",
  "300282" :"跨主存储迁移云盘失败",
  "300283" :"跨主存储迁移云主机失败",
  "300284" :"获取存储迁移候选列表失败",
  "300285" :"获取主存储的License信息失败",
  "300286" :"添加本地存储为主存储失败",
  "300287" :"查询本地存储资源引用失败",
  "300288" :"迁移本地存储上存放的云盘失败",
  "300289" :"获取主机本地存储容量失败",
  "300290" :"获取迁移本地存储物理机失败",
  "300291" :"添加NFS主存储失败",
  "300292" :"添加一个共享挂载点的主存储失败",
  "300293" :"添加Ceph主存储失败",
  "300294" :"查询Ceph主存储失败",
  "300295" :"为Ceph主存储添加mon节点失败",
  "300296" :"从Ceph主存储删除mon节点失败",
  "300297" :"更新Ceph主存储mon节点失败",
  "300298" :"添加Ceph主存储池失败",
  "300299" :"删除Ceph主存储池失败",
  "300300" :"查询Ceph主存储池失败",
  "300301" :"更新Ceph主存储池失败",
  "300302" :"添加Shared Block主存储失败",
  "300303" :"查询连接状态失败",
  "300304" :"查询Shared Block主存储失败",
  "300305" :"添加LUN到Shared Block主存储失败",
  "300306" :"获取共享块设备候选清单失败",
  "300307" :"刷新共享块设备容量失败",
  "300308" :"更新共享块存储中共享块的diskUuid失败",
  "300309" :"查询共享块设备失败",
  "300310" :"删除镜像服务器失败",
  "300311" :"查询镜像服务器失败",
  "300312" :"重连镜像服务器失败",
  "300313" :"更改镜像服务器可用状态失败",
  "300314" :"获取镜像服务器存储容量失败",
  "300315" :"获取镜像服务器类型列表失败",
  "300316" :"更新镜像服务器信息失败",
  "300317" :"从镜像服务器导出镜像失败",
  "300318" :"从镜像服务器删除导出的镜像失败",
  "300319" :"挂载镜像服务器至区域失败",
  "300320" :"从区域中卸载已经挂载的镜像服务器失败",
  "300321" :"跨镜像服务器迁移镜像失败",
  "300322" :"获取候选列表失败",
  "300323" :"添加镜像仓库服务器失败",
  "300324" :"查询镜像仓库服务器失败",
  "300325" :"重连镜像仓库服务器失败",
  "300326" :"更新镜像仓库服务器信息失败",
  "300327" :"更新镜像仓库服务器信息失败",
  "300328" :"添加Ceph镜像服务器失败",
  "300329" :"查询Ceph镜像服务器失败",
  "300330" :"更新Ceph镜像服务器mon节点失败",
  "300331" :"Ceph镜像服务器添加mon节点失败",
  "300332" :"Ceph镜像服务器删除mon节点失败",
  "300333" :"查询SCSI Lun失败",
  "300334" : "将LUN设备从物理机卸载失败",
  "300335" :"添加iSCSI服务器失败",
  "300336" :"删除iSCSI服务器失败",
  "300337" :"查询iSCSI服务器失败",
  "300338" :"刷新iSCSI服务器失败",
  "300339" :"更新iSCSI服务器配置失败",
  "300340" :"将iSCSI服务器加载到集群失败",
  "300341" :"将iSCSI服务器从集群卸载失败",
  "300342" :"查询iSCSI磁盘失败",
  "300343" :"查询FC SAN存储失败",
  "300344" :"刷新FC SAN存储失败",
  "300345" :"更新SCSI LUN配置失败",
  "300346" :"将SCSI LUN加载到云主机失败",
  "300347" :"将SCSI LUN从云主机卸载失败",
  "300348" :"检查SCSI Lun与集群连接关系失败",
  "300349" :"获取可加载的SCSI Lun失败",
  "300350" :"添加SDN控制器失败",
  "300351" :"查询SDN控制器失败",
  "300352" :"删除SDN控制器失败",
  "300353" :"更新SDN控制器失败",
  "300354" :"创建VXLAN网络池失败",
  "300355" :"查询VXLAN网络池失败",
  "300356" :"创建VXLAN网络池失败",
  "300357" :"查询VXLAN网络失败",
  "300358" :"创建普通二层网络失败",
  "300359" :"创建二层VLAN网络失败",
  "300360" :"查询二层VLAN网络失败",
  "300361" :"删除二层网络失败",
  "300362" :"查询二层网络失败",
  "300363" :"更新二层网络失败",
  "300364" :"获取二层网络类型失败",
  "300365" :"挂载二层网络到集群失败",
  "300366" :"从集群上卸载二层网络失败",
  "300367" :"创建Vni Range失败",
  "300368" :"查询Vni Range失败",
  "300369" :"删除Vni Range失败",
  "300370" :"修改Vni Range失败",
  "300371" :"创建三层网络失败",
  "300372" :"删除三层网络失败",
  "300373" :"查询三层网络失败",
  "300374" :"更新三层网络失败",
  "300375" :"获取三层网络类型失败",
  "300376" :"改变三层网络状态失败",
  "300377" :"获取网络DHCP服务所用地址失败",
  "300378" :"向三层网络添加DNS失败",
  "300379" :"从三层网络移除DNS失败",
  "300380" :"向三层网络添加主机路由失败",
  "300381" :"从三层网络移除主机路由失败",
  "300382" :"获取空闲IP失败",
  "300383" :"检查IP可用性失败",
  "300384" :"获取IP网络地址容量失败",
  "300385" :"获取IP网络地址容量失败",
  "300386" :"删除IP地址范围失败",
  "300387" :"查询IP地址范围失败",
  "300388" :"更新IP地址范围失败",
  "300389" :"通过网络CIDR添加IP地址范围失败",
  "300390" :"获取三层网络Mtu值失败",
  "300391" :"设置三层网络Mtu值失败",
  "300392" :"获取三层网络上路由器的接口地址失败",
  "300393" :"设置三层网络路由器接口IP失败",
  "300394" :"添加IPv6地址范围失败",
  "300395" :"通过网络CIDR添加IPv6地址范围失败",
  "300396" :"查询IP地址失败",
  "300397" :"获取三层网络IP地址使用情况统计失败",
  "300398" :"查询IP地址池失败",
  "300399" :"重连云路由器失败",
  "300400" :"查询云路由器失败",
  "300401" :"查询服务云主机失败",
  "300402" :"创建云路由规格失败",
  "300403" :"查询云路由规格失败",
  "300404" :"更新云路由规格失败",
  "300405" :"获取云路由器可加载外部网络失败",
  "300406" :"创建云路由路由表失败",
  "300407" :"删除云路由路由表失败",
  "300408" :"查询云路由路由表失败",
  "300409" :"获取路由器实时路由表失败",
  "300410" :"添加云路由路由条目失败",
  "300411" :"删除云路由路由条目失败",
  "300412" :"查询云路由路由条目失败",
  "300413" :"绑定云路由路由表到云路由器失败",
  "300414" :"解绑云路由路由表失败",
  "300415" :"查询绑定关系失败",
  "300416" :"创建VPC路由器失败",
  "300417" :"查询VPC路由器失败",
  "300418" :"获取VPC路由器可加载的三层网络失败",
  "300419" :"获取实时流量状态失败",
  "300420" :"获取分布式路由是否打开失败",
  "300421" :"设置分布式路由开关失败",
  "300422" :"向VPC路由器添加DNS失败",
  "300423" :"从VPC路由器移除DNS失败",
  "300424" :"获取VPC路由器的网络服务状态失败",
  "300425" :"设置VPC路由器的网络服务失败",
  "300426" :"更新高可用组仲裁ip失败",
  "300427" :"创建高可用组失败",
  "300428" :"删除高可用组失败",
  "300429" :"更新高可用组失败",
  "300430" :"查询高可用失败",
  "300431" :"更新虚拟路由器失败",
  "300432" :"创建路由区域资源失败",
  "300433" :"删除OSPF路由区域失败",
  "300434" :"获取OSPF的邻居信息失败",
  "300435" :"查询OSPF路由区域信息失败",
  "300436" :"获取路由器的ID失败",
  "300437" :"设置路由器的ID失败",
  "300438" :"添加网络到OSPF的区域失败",
  "300439" :"从路由区域中移除网络失败",
  "300440" :"更改OSPF的路由区域属性失败",
  "300441" :"查询路由加入到区域的网络信息失败",
  "300442" :"创建组播路由器失败",
  "300443" :"删除组播路由器失败",
  "300444" :"查询组播路由器失败",
  "300445" :"改变组播路由器状态失败",
  "300446" :"获取组播路由表失败",
  "300447" :"添加组播路由静态RP地址失败",
  "300448" :"删除组播路由器静态RP地址失败",
  "300449" :"创建策略路由规则集失败",
  "300450" :"删除策略路由规则集失败",
  "300451" :"更新策略路由规则集属性失败",
  "300452" :"查询策略路由规则集失败",
  "300453" :"查询策略路由规则集网络关联失败",
  "300454" :"查询策略路由规则集与单节点云路由关联失败",
  "300455" :"创建策略路由规则集规则失败",
  "300456" :"删除策略路由规则集规则失败",
  "300457" :"创建策略路由表失败",
  "300458" :"删除策略路由表失败",
  "300459" :"查询策略路由表失败",
  "300460" :"查询策略路由表与单节点云路由关联失败",
  "300461" :"创建策略路由失败",
  "300462" :"删除策略路由失败",
  "300463" :"查询策略路由失败",
  "300464" :"查询策略路由规则失败",
  "300465" :"网络加载策略路由规则集失败",
  "300466" :"网络解绑策略路由失败",
  "300467" :"获取虚拟路由器的策略路由集合失败",
  "300468" :"获取网络服务类型失败",
  "300469" :"查询网络服务模块失败",
  "300470" :"查询网络服务与三层网络引用失败",
  "300471" :"挂载网络服务到三层网络失败",
  "300472" :"从三层网络卸载网络服务失败",
  "300473" :"创建防火墙失败",
  "300474" :"查询防火墙失败",
  "300475" :"更新防火墙失败",
  "300476" :"刷新防火墙配置失败",
  "300477" :"删除防火墙失败",
  "300478" :"创建防火墙规则集失败",
  "300479" :"查询防火墙规则集失败",
  "300480" :"更新防火墙规则集失败",
  "300481" :"删除防火墙规则集失败",
  "300482" :"网络加载防火墙规则集失败",
  "300483" :"网络卸载防火墙规则集失败",
  "300484" :"查询防火墙规则集与三层网络关联关系失败",
  "300485" :"创建防火墙规则失败",
  "300486" :"查询防火墙规则失败",
  "300487" :"更新防火墙规则失败",
  "300488" :"删除防火墙规则失败",
  "300489" :"更改防火墙规则状态失败",
  "300490" :"创建防火墙规则模板失败",
  "300491" :"删除防火墙规则模板失败",
  "300492" :"更新防火墙规则模板失败",
  "300493" :"查询防火墙规则模板失败",
  "300494" :"查询防火墙与单节点路由器关联关系失败",
  "300495" :"下发规则集更改内容到路由器失败",
  "300496" :"创建防火墙IP或端口模板失败",
  "300497" :"删除防火墙IP或端口模板失败",
  "300498" :"更新防火墙IP或端口模板失败",
  "300499" :"查询防火墙IP或端口模板失败",
  "300500" :"创建安全组失败",
  "300501" :"删除安全组失败",
  "300502" :"查询安全组失败",
  "300503" :"更新安全组失败",
  "300504" :"改变安全组状态失败",
  "300505" :"挂载安全组到L3网络失败",
  "300506" :"从L3网络卸载安全组失败",
  "300507" :"获取网卡列表清单失败",
  "300508" :"添加虚拟机网卡到安全组失败",
  "300509" :"从安全组删除虚拟机网卡失败",
  "300510" :"查询应用了安全组的网卡列表失败",
  "300511" :"添加规则到安全组失败",
  "300512" :"查询安全组规则失败",
  "300513" :"删除安全组规则失败",
  "300514" :"创建虚拟IP失败",
  "300515" :"删除虚拟IP失败",
  "300516" :"查询虚拟IP失败",
  "300517" :"更新虚拟IP失败",
  "300518" :"更改虚拟IP启用状态失败",
  "300519" :"获取虚拟IP所有业务端口列表失败",
  "300520" :"设置虚拟IP限速失败",
  "300521" :"获取虚拟IP限速失败",
  "300522" :"取消虚拟IP限速失败",
  "300523" :"创建弹性IP失败",
  "300524" :"删除弹性IP失败",
  "300525" :"查询弹性IP失败",
  "300526" :"更新弹性IP失败",
  "300527" :"更改虚拟IP启用状态失败",
  "300528" :"获取可绑定指定弹性IP的云主机网卡失败",
  "300529" :"绑定弹性IP失败",
  "300530" :"解绑弹性IP失败",
  "300531" :"创建端口转发规则失败",
  "300532" :"删除端口转发规则失败",
  "300533" :"查询端口转发规则失败",
  "300534" :"更新端口转发规则失败",
  "300535" :"改变端口转发规则的状态失败",
  "300536" :"获取云主机网卡列表失败",
  "300537" :"挂载规则到虚拟机网卡上失败",
  "300538" :"从虚拟机网卡卸载规则失败",
  "300539" :"创建负载均衡器失败",
  "300540" :"删除负载均衡器失败",
  "300541" :"查询负载均衡器失败",
  "300542" :"刷新负载均衡器失败",
  "300543" :"创建负载均衡监听器失败",
  "300544" :"删除负载均衡监听器失败",
  "300545" :"查询负载均衡监听器失败",
  "300546" :"更新负载均衡监听器失败",
  "300547" :"修改负载均衡监听器参数失败",
  "300548" :"获取云主机网卡失败",
  "300549" :"添加云主机网卡到负载均衡器失败",
  "300550" :"从负载均衡器移除云主机网卡失败",
  "300551" :"更新负载均衡器失败",
  "300552" :"创建证书失败",
  "300553" :"删除证书失败",
  "300554" :"查询证书失败",
  "300555" :"添加证书到负载均衡失败",
  "300556" :"从负载均衡移除证书失败",
  "300557" :"更新证书信息失败",
  "300558" :"添加转发规则到访问控制策略组失败",
  "300559" :"修改控制策略组转发规则名称失败",
  "300560" :"修改访问控制组绑定的后端服务器组失败",
  "300561" :"获取负载均衡监听器访问控制策略条目失败",
  "300562" :"创建访问控制策略组失败",
  "300563" :"删除访问控制策略组失败",
  "300564" :"查询访问控制策略组失败",
  "300565" :"向访问控制策略组添加IP组失败",
  "300566" :"删除访问控制策略的IP组失败",
  "300567" :"添加监听器的访问控制策略失败",
  "300568" :"删除监听器访问控制策略失败",
  "300569" :"获取监听器可加载L3网络失败",
  "300570" :"创建负载均衡器服务器组失败",
  "300571" :"删除负载均衡器服务器组失败",
  "300572" :"更新负载均衡器服务器组失败",
  "300573" :"查询负载均衡器服务器组失败",
  "300574" :"添加后端服务器到服务器组失败",
  "300575" :"从服务器组移除后端服务器失败",
  "300576" :"添加服务器组到负载均衡监听器失败",
  "300577" :"从负载均衡监听器移除服务器组失败",
  "300578" :"更新负载均衡后端服务器参数失败",
  "300579" :"获取可供负载均衡器服务器组添加的云主机网卡失败",
  "300580" :"创建性能独享型负载均衡器组失败",
  "300581" :"删除性能独享型负载均衡器组失败",
  "300582" :"更新性能独享型负载均衡器组失败",
  "300583" :"查询性能独享型负载均衡器组失败",
  "300584" :"创建高性能实例性负载均衡器规格失败",
  "300585" :"查询性能独享型负载均衡器规格失败",
  "300586" :"创建高性能负载均衡器实例失败",
  "300587" :"创建IPsec连接失败",
  "300588" :"删除IPsec连接失败",
  "300589" :"更新IPsec连接失败",
  "300590" :"查询IPsec连接失败",
  "300591" :"更改IPsec连接状态失败",
  "300592" :"添加三层网络到IPsec连接失败",
  "300593" :"从IPsec连接删除三层网络失败",
  "300594" :"添加远端CIDR到IPsec连接失败",
  "300595" :"删除远端CIDR失败",
  "300596" :"创建流量监控搜集器失败",
  "300597" :"查询流量监控的搜集器失败",
  "300598" :"更新搜集器信息失败",
  "300599" :"删除流量监控搜集器失败",
  "300600" :"创建流量监控资源失败",
  "300601" :"查询流量监控资源失败",
  "300602" :"更新流量监控的信息失败",
  "300603" :"删除流量监控资源失败",
  "300604" :"添加VPC路由器网络到FlowMeter中失败",
  "300605" :"查询开启流量监控的VPC网络失败",
  "300606" :"流量监控的统计信息失败",
  "300607" :"清除VPC路由器网络的流量监控失败",
  "300608" :"获取流量监控协议中使用的系统标识失败",
  "300609" :"设置流量监控协议使用的VPC标识失败",
  "300610" :"创建端口镜像失败",
  "300611" :"查询端口镜像失败",
  "300612" :"更新端口镜像失败",
  "300613" :"删除端口镜像失败",
  "300614" :"创建端口镜像会话失败",
  "300615" :"查询端口镜像会话失败",
  "300616" :"更新端口镜像服务状态失败",
  "300617" :"删除端口镜像会话失败",
  "300618" :"获取系统中可以使用端口镜像服务的网卡失败",
  "300619" :"查询端口镜像网络分配的IP失败",
  "300620" :"添加资源栈模板失败",
  "300621" :"删除资源栈模板失败",
  "300622" :"查询资源栈模板失败",
  "300623" :"修改资源栈模板失败",
  "300624" :"获取支持的资源列表失败",
  "300625" :"创建资源栈失败",
  "300626" :"预览资源栈失败",
  "300627" :"删除资源栈失败",
  "300628" :"修改资源栈失败",
  "300629" :"查询资源栈失败",
  "300630" :"获取资源栈内资源列表失败",
  "300631" :"查询资源栈内事件列表失败",
  "300632" :"重启资源栈失败",
  "300633" :"检查资源栈模板参数失败",
  "300634" :"从资源编排模板解析成资源关系图失败",
  "300635" :"获取资源对应的资源栈失败",
  "300636" :"获取资源栈中云主机端口监控状态失败",
  "300637" :"添加资源栈中云主机端口监控失败",
  "300638" :"删除资源栈中云主机端口监控失败",
  "300639" :"获取所有metric元数据失败",
  "300640" :"获取metric的标签值失败",
  "300641" :"获取metric数据失败",
  "300642" :"存入自定义metric数据失败",
  "300643" :"获取所有event元数据失败",
  "300644" :"获取事件失败",
  "300645" :"更新事件失败",
  "300646" :"查询事件报警器报警记录",
  "300647" :"创建报警器失败",
  "300648" :"删除报警器失败",
  "300649" :"修改报警器失败",
  "300650" :"修改事件报警器失败",
  "300651" :"增加报警动作失败",
  "300652" :"删除报警动作失败",
  "300653" :"增加标签到报警器失败",
  "300654" :"修改报警器标签失败",
  "300655" :"从报警器上删除标签失败",
  "300656" :"更改报警器状态失败",
  "300657" :"查询报警器失败",
  "300658" :"获取报警器历史失败",
  "300659" :"更新报警器历史消息失败",
  "300660" : "统计报警消息数量",
  "300661" : "查询资源报警器报警记录",
  "300662" :"订阅事件失败",
  "300663" :"退订事件失败",
  "300664" :"查询事件订阅失败",
  "300665" :"更新事件订阅的标签失败",
  "300666" :"创建报警消息模板失败",
  "300667" :"删除报警消息模板失败",
  "300668" :"更新报警消息模板失败",
  "300669" :"查询报警消息模板失败",
  "300670" :"创建SNS监控阿里云短信模板失败",
  "300671" :"更新SNS阿里云短信文本模板失败",
  "300672" :"查询SNS监控阿里云短信模板失败",
  "300673" :"获取审计数据失败",
  "300674" :"创建主题失败",
  "300675" :"删除主题失败",
  "300676" :"更改主题状态失败",
  "300677" :"更新主题失败",
  "300678" :"查询主题失败",
  "300679" :"创建邮件服务器失败",
  "300680" :"测试邮件服务器失败",
  "300681" :"删除SNS应用平台失败",
  "300682" :"查询邮件服务器失败",
  "300683" :"更新SNS应用平台失败",
  "300684" :"查询SNS应用平台失败",
  "300685" :"更改SNS应用平台状态失败",
  "300686" :"创建邮件接收端失败",
  "300687" :"查询邮件接收端失败",
  "300688" :"创建HTTP接收端失败",
  "300689" :"查询HTTP接收端失败",
  "300690" :"创建钉钉接收端失败",
  "300691" :"添加钉钉用户失败",
  "300692" :"删除钉钉用户失败",
  "300693" :"查询钉钉终端失败",
  "300694" :"删除接收端失败",
  "300695" :"更新接收端失败",
  "300696" :"查询接收端失败",
  "300697" :"更改接收端失败",
  "300698" :"创建阿里云短信接收端失败",
  "300699" :"验证阿里云短信接收端失败",
  "300700" :"添加短信接收者失败",
  "300701" :"删除短信接收者失败",
  "300702" :"查询短信接收端失败",
  "300703" :"添加邮箱地址到邮箱接收端失败",
  "300704" :"更新接收端邮箱地址失败",
  "300705" :"删除邮箱接收端的地址失败",
  "300706" :"查询接收端邮箱地址失败",
  "300707" :"创建微软Teams接收端失败",
  "300708" :"查询微软Teams接收端失败",
  "300709" :"订阅主题失败",
  "300710" :"查询订阅主题的终端失败",
  "300711" :"退订主题失败",
  "300712" : "获取管理节点目录容量",
  "300713" :"查询管理节点失败",
  "300714" :"获取当前版本失败",
  "300715" :"获取当前时间失败",
  "300716" : "获取管理节点当前的时区信息",
  "300717" :"检查管理节点是否能正常开始工作失败",
  "300718" : "获取管理节点操作系统信息",
  "300719" : "获取管理节点CPU架构类型",
  "300720" :"创建系统标签失败",
  "300721" :"查询系统标签失败",
  "300722" :"更新系统标签失败",
  "300723" :"创建用户标签失败",
  "300724" :"查询用户标签失败",
  "300725" :"删除标签失败",
  "300726" :"创建资源标签失败",
  "300727" :"查询资源标签失败",
  "300728" :"更新资源标签失败",
  "300729" :"加载资源标签失败",
  "300730" :"卸载资源标签失败",
  "300731" :"获取任务进度失败",
  "300732" :"获取CPU和内存容量失败",
  "300733" :"触发垃圾回收任务失败",
  "300734" :"删除垃圾回收任务失败",
  "300735" :"查询垃圾回收任务失败",
  "300736" :"获取许可证信息失败",
  "300737" :"获取许可证历史授权信息",
  "300738" :"获取许可证容量失败",
  "300739" :"删除许可证文件失败",
  "300740" :"重新加载许可证失败",
  "300741" :"更新许可证信息失败",
  "300742" :"提交长时任务失败",
  "300743" :"更新长时任务失败",
  "300744" :"删除长时任务失败",
  "300745" :"查询长时任务失败",
  "300746" :"查看系统错误码失败",
  "300747" :"重新生成索引",
  "300748" :"创建资源价格失败",
  "300749" :"删除资源价格失败",
  "300750" :"修改资源价格失败",
  "300751" :"查询资源价格失败",
  "300752" :"计算账户花费失败",
  "300753" :"查询账户账单失败",
  "300754" :"创建计费价目失败",
  "300755" :"删除计费价目失败",
  "300756" :"修改计费价目失败",
  "300757" :"查询计费价目失败",
  "300758" :"为账户项目指定计费价目失败",
  "300759" :"取消账户项目关联的计费价目失败",
  "300760" :"修改账户项目计费价目失败",
  "300761" :"获得项目账户使用的计费价目失败",
  "300762" :"查询账户项目与计费价目的关联关系失败",
  "300763" :"生成账单失败",
  "300764" :"请求控制台访问地址失败",
  "300765" :"查询控制台代理失败",
  "300766" :"重连控制台代理失败",
  "300767" :"更新控制台代理失败",
  "300768" :"增加IP访问控制规则失败",
  "300769" :"删除IP访问控制规则失败",
  "300770" :"更新IP访问控制规则失败",
  "300771" :"查询IP访问控制规则失败",
  "300772" :"创建AccessKey失败",
  "300773" :"删除AccessKey失败",
  "300774" :"查询AccessKey失败",
  "300775" :"开启或关闭AccessKey失败",
  "300776" :"添加日志服务器配置失败",
  "300777" :"删除日志服务器配置失败",
  "300778" :"获取日志服务器配置失败",
  "300779" :"修改日志服务器配置失败",
  "300780" :"添加AD/LDAP服务器失败",
  "300781" :"删除AD/LDAP服务器失败",
  "300782" :"查询AD/LDAP服务器失败",
  "300783" :"更新AD/LDAP服务器失败",
  "300784" :"创建AD/LDAP绑定失败",
  "300785" :"删除AD/LDAP绑定失败",
  "300786" :"查询AD/LDAP绑定失败",
  "300787" :"清理无效的AD/LDAP绑定失败",
  "300788" :"使用AD/LDAP身份登录失败",
  "300789" :"获取AD/LDAP条目失败",
  "300790" :"获取可绑定的AD/LDAP条目失败",
  "300791" :"查询全局设置失败",
  "300792" :"更新全局设置失败",
  "300793" :"重置全局配置失败",
  "300794" :"获取资源的资源高级设置失败",
  "300795" :"获取可配置的资源高级设置失败",
  "300796" :"删除资源的资源高级设置失败",
  "300797" :"查询资源高级设置失败",
  "300798" :"更新资源高级设置失败",
  "300799" :"应用模板失败",
  "300800" :"查询所有模板信息失败",
  "300801" :"查询模板具体配置失败",
  "300802" :"更新模板值失败",
  "300803" :"重置模板到初始状态失败",
  "300804" :"创建账户失败",
  "300805" :"删除账户失败",
  "300806" :"查询账户失败",
  "300807" :"更新账户失败",
  "300808" :"使用账户身份登录失败",
  "300809" :"获取登录验证码失败",
  "300810" :"刷新验证码失败",
  "300811" :"获取双因子认证密匙失败",
  "300812" :"查询双因子认证密匙失败",
  "300813" :"获取双因子认证状态失败",
  "300814" :"获取账户配额使用情况失败",
  "300815" :"查询账户资源引用失败",
  "300816" :"共享资源给账户失败",
  "300817" :"创建用户组失败",
  "300818" :"删除用户组失败",
  "300819" :"查询用户组失败",
  "300820" :"更新用户组失败",
  "300821" :"添加到用户组失败",
  "300822" :"绑定策略到用户组失败",
  "300823" :"将策略从用户组解绑失败",
  "300824" :"从用户组中移除用户失败",
  "300825" :"创建用户失败",
  "300826" :"删除用户失败",
  "300827" :"查询用户失败",
  "300828" :"更新用户失败",
  "300829" :"使用用户身份登录失败",
  "300830" :"绑定一条策略到用户失败",
  "300831" :"将一条策略从用户解绑失败",
  "300832" :"绑定多条策略到用户失败",
  "300833" :"将多条策略从用户解绑失败",
  "300834" :"创建策略失败",
  "300835" :"删除策略失败",
  "300836" :"查询策略失败",
  "300837" :"查询配额失败",
  "300838" :"更新配额失败",
  "300839" :"获取资源名称失败",
  "300840" :"查询共享资源失败",
  "300841" :"解除资源共享失败",
  "300842" :"变更资源所有者失败",
  "300843" :"检查API权限失败",
  "300844" :"验证会话的有效性失败",
  "300845" :"更新会话失败",
  "300846" :"退出当前登录状态失败",
  "300847" :"创建定时器失败",
  "300848" :"删除定时器失败",
  "300849" :"查询定时器失败",
  "300850" :"更新定时器失败",
  "300851" :"添加定时任务到定时器失败",
  "300852" :"从定时器移除定时任务失败",
  "300853" :"创建定时任务失败",
  "300854" :"删除定时任务失败",
  "300855" :"查询定时任务失败",
  "300856" :"更新定时任务失败",
  "300857" :"获取未挂载定时器的任务失败",
  "300858" :"改变定时任务状态失败",
  "300859" :"添加vCenter资源失败",
  "300860" :"查询vCenter资源失败",
  "300861" :"删除vCenter资源失败",
  "300862" :"更新vCenter资源失败",
  "300863" :"同步vCenter资源失败",
  "300864" :"查询vCenter集群失败",
  "300865" :"查询vCenter主存储失败",
  "300866" :"查询vCenter镜像服务器失败",
  "300867" :"查询vCenter资源池失败"
}